opb-33-nspkg.pth
opb/clocked.py
opb/handler.py
opb/loggers.py
opb/objects.py
opb/persist.py
opb/runtime.py
opb/scanner.py
opb/threads.py
opb/utility.py
opb/modules/cmd.py
opb/modules/err.py
opb/modules/flt.py
opb/modules/fnd.py
opb/modules/irc.py
opb/modules/log.py
opb/modules/rss.py
opb/modules/sts.py
opb/modules/tdo.py
opb/modules/thr.py
opb/modules/upt.py
opb/modules/usr.py
opb-33.data/data/opb/README.rst
opb-33.data/scripts/opb
opb-33.data/scripts/opbc
opb-33.data/scripts/opbd
opb-33.dist-info/METADATA
opb-33.dist-info/WHEEL
opb-33.dist-info/namespace_packages.txt
opb-33.dist-info/top_level.txt
opb-33.dist-info/zip-safe
opb-33.dist-info/RECORD
